examples/alu.v
// ALU 模块
module alu #(
    parameter WIDTH = 8
)(
    input  [WIDTH-1:0] a,
    input  [WIDTH-1:0] b,
    input  [2:0]       op,
    output reg [WIDTH-1:0] result,
    output              zero
);

    localparam OP_ADD = 3'b000;
    localparam OP_SUB = 3'b001;
    localparam OP_AND = 3'b010;
    localparam OP_OR  = 3'b011;
    localparam OP_XOR = 3'b100;
    localparam OP_NOT = 3'b101;
    localparam OP_SHL = 3'b110;
    localparam OP_SHR = 3'b111;

    always @(*) begin
        case (op)
            OP_ADD: result = a + b;
            OP_SUB: result = a - b;
            OP_AND: result = a & b;
            OP_OR:  result = a | b;
            OP_XOR: result = a ^ b;
            OP_NOT: result = ~a;
            OP_SHL: result = a << 1;
            OP_SHR: result = a >> 1;
            default: result = {WIDTH{1'b0}};
        endcase
    end

    assign zero = (result == 0);

endmodule

examples/tb_alu.v
// ALU 测试平台
`timescale 1ns/1ps

module tb_alu;

    parameter WIDTH = 8;

    reg  [WIDTH-1:0] a, b;
    reg  [2:0]       op;
    wire [WIDTH-1:0] result;
    wire             zero;

    // 实例化 ALU
    alu #(.WIDTH(WIDTH)) uut (
        .a(a),
        .b(b),
        .op(op),
        .result(result),
        .zero(zero)
    );

    initial begin
        // 测试加法
        a = 8'd10; b = 8'd5; op = 3'b000;
        #10;
        $display("ADD: %0d + %0d = %0d", a, b, result);

        // 测试减法
        a = 8'd10; b = 8'd10; op = 3'b001;
        #10;
        $display("SUB: %0d - %0d = %0d (zero=%b)", a, b, result, zero);

        // 测试 AND
        a = 8'b1010; b = 8'b1100; op = 3'b010;
        #10;
        $display("AND: %b & %b = %b", a, b, result);

        // 测试完成
        #100;
        $display("PASS");
        $finish;
    end

    // 波形输出
    initial begin
        $dumpfile("tb_alu.vcd");
        $dumpvars(0, tb_alu);
    end

    // 超时保护
    initial begin
        #100000;
        $display("TIMEOUT");
        $finish;
    end

endmodule

examples/counter.v
// 4位计数器示例
module counter (
    input clk,
    input rst_n,
    output reg [3:0] count
);

    always @(posedge clk or negedge rst_n) begin
        if (!rst_n)
            count <= 4'b0;
        else
            count <= count + 1'b1;
    end

endmodule

examples/counter_tb.v
// 4位计数器测试平台
`timescale 1ns/1ps

module counter_tb;

    // 时钟和复位
    reg clk;
    reg rst_n;

    // 待测模块信号
    wire [3:0] count;

    // 实例化待测模块
    counter uut (
        .clk(clk),
        .rst_n(rst_n),
        .count(count)
    );

    // 时钟生成
    initial begin
        clk = 0;
        forever #5 clk = ~clk;
    end

    // 测试激励
    initial begin
        // 复位
        rst_n = 0;
        #20;
        rst_n = 1;

        // 运行 100 个时钟周期
        #1000;

        // 检查结果
        $display("Test completed. Final count: %d", count);
        $display("PASS");
        $finish;
    end

    // 波形输出
    initial begin
        $dumpfile("counter_tb.vcd");
        $dumpvars(0, counter_tb);
    end

    // 超时保护
    initial begin
        #100000;
        $display("TIMEOUT");
        $finish;
    end

endmodule

simulation.vcd
$date
	Sun Jun 14 17:20:11 2026
$end
$version
	Icarus Verilog
$end
$timescale
	1ps
$end
$scope module counter_tb $end
$var wire 4 ! count [3:0] $end
$var reg 1 " clk $end
$var reg 1 # rst_n $end
$scope module uut $end
$var wire 1 " clk $end
$var wire 1 # rst_n $end
$var reg 4 $ count [3:0] $end
$upscope $end
$upscope $end
$scope module tb_alu $end
$var wire 1 % zero $end
$var wire 8 & result [7:0] $end
$var parameter 32 ' WIDTH $end
$var reg 8 ( a [7:0] $end
$var reg 8 ) b [7:0] $end
$var reg 3 * op [2:0] $end
$scope module uut $end
$var wire 8 + a [7:0] $end
$var wire 8 , b [7:0] $end
$var wire 3 - op [2:0] $end
$var wire 1 % zero $end
$var parameter 3 . OP_ADD $end
$var parameter 3 / OP_AND $end
$var parameter 3 0 OP_NOT $end
$var parameter 3 1 OP_OR $end
$var parameter 3 2 OP_SHL $end
$var parameter 3 3 OP_SHR $end
$var parameter 3 4 OP_SUB $end
$var parameter 3 5 OP_XOR $end
$var parameter 32 6 WIDTH $end
$var reg 8 7 result [7:0] $end
$upscope $end
$upscope $end
$enddefinitions $end
$comment Show the parameter values. $end
$dumpall
b1000 6
b100 5
b1 4
b111 3
b110 2
b11 1
b101 0
b10 /
b0 .
b1000 '
$end
#0
$dumpvars
b1111 7
b0 -
b101 ,
b1010 +
b0 *
b101 )
b1010 (
b1111 &
0%
b0 $
0#
0"
b0 !
$end
#5000
1"
#10000
1%
b0 &
b0 7
0"
b1 *
b1 -
b1010 )
b1010 ,
#15000
1"
#20000
0%
b1000 &
b1000 7
0"
b10 *
b10 -
b1100 )
b1100 ,
1#
#25000
b1 !
b1 $
1"
#30000
0"
#35000
b10 !
b10 $
1"
#40000
0"
#45000
b11 !
b11 $
1"
#50000
0"
#55000
b100 !
b100 $
1"
#60000
0"
#65000
b101 !
b101 $
1"
#70000
0"
#75000
b110 !
b110 $
1"
#80000
0"
#85000
b111 !
b111 $
1"
#90000
0"
#95000
b1000 !
b1000 $
1"
#100000
0"
#105000
b1001 !
b1001 $
1"
#110000
0"
#115000
b1010 !
b1010 $
1"
#120000
0"
#125000
b1011 !
b1011 $
1"
