examples/counter.v
// 4位计数器示例
module counter (
    input clk,
    input rst_n,
    output reg [3:0] count
);

    always @(posedge clk or negedge rst_n) begin
        if (!rst_n)
            count <= 4'b0;
        else
            count <= count + 1'b1;
    end

endmodule

examples/counter_tb.v
// 4位计数器测试平台
`timescale 1ns/1ps

module counter_tb;

    // 时钟和复位
    reg clk;
    reg rst_n;

    // 待测模块信号
    wire [3:0] count;

    // 实例化待测模块
    counter uut (
        .clk(clk),
        .rst_n(rst_n),
        .count(count)
    );

    // 时钟生成
    initial begin
        clk = 0;
        forever #5 clk = ~clk;
    end

    // 测试激励
    initial begin
        // 复位
        rst_n = 0;
        #20;
        rst_n = 1;

        // 运行 100 个时钟周期
        #1000;

        // 检查结果
        $display("Test completed. Final count: %d", count);
        $display("PASS");
        $finish;
    end

    // 波形输出
    initial begin
        $dumpfile("counter_tb.vcd");
        $dumpvars(0, counter_tb);
    end

    // 超时保护
    initial begin
        #100000;
        $display("TIMEOUT");
        $finish;
    end

endmodule

simulation.vcd
$date
	Sun Jun 14 14:01:35 2026
$end
$version
	Icarus Verilog
$end
$timescale
	1ps
$end
$scope module counter_tb $end
$var wire 4 ! count [3:0] $end
$var reg 1 " clk $end
$var reg 1 # rst_n $end
$scope module uut $end
$var wire 1 " clk $end
$var wire 1 # rst_n $end
$var reg 4 $ count [3:0] $end
$upscope $end
$upscope $end
$enddefinitions $end
$comment Show the parameter values. $end
$dumpall
$end
#0
$dumpvars
b0 $
0#
0"
b0 !
$end
#5000
1"
#10000
0"
#15000
1"
#20000
0"
1#
#25000
b1 !
b1 $
1"
#30000
0"
#35000
b10 !
b10 $
1"
#40000
0"
#45000
b11 !
b11 $
1"
#50000
0"
#55000
b100 !
b100 $
1"
#60000
0"
#65000
b101 !
b101 $
1"
#70000
0"
#75000
b110 !
b110 $
1"
#80000
0"
#85000
b111 !
b111 $
1"
#90000
0"
#95000
b1000 !
b1000 $
1"
#100000
0"
#105000
b1001 !
b1001 $
1"
#110000
0"
#115000
b1010 !
b1010 $
1"
#120000
0"
#125000
b1011 !
b1011 $
1"
#130000
0"
#135000
b1100 !
b1100 $
1"
#140000
0"
#145000
b1101 !
b1101 $
1"
#150000
0"
#155000
b1110 !
b1110 $
1"
#160000
0"
#165000
b1111 !
b1111 $
1"
#170000
0"
#175000
b0 !
b0 $
1"
#180000
0"
#185000
b1 !
b1 $
1"
#190000
0"
#195000
b10 !
b10 $
1"
#200000
0"
#205000
b11 !
b11 $
1"
#210000
0"
#215000
b100 !
b100 $
1"
#220000
0"
#225000
b101 !
b101 $
1"
#230000
0"
#235000
b110 !
b110 $
1"
#240000
0"
#245000
b111 !
b111 $
1"
#250000
0"
#255000
b1000 !
b1000 $
1"
#260000
0"
#265000
b1001 !
b1001 $
1"
#270000
0"
#275000
b1010 !
b1010 $
1"
#280000
0"
#285000
b1011 !
b1011 $
1"
#290000
0"
#295000
b1100 !
b1100 $
1"
#300000
0"
#305000
b1101 !
b1101 $
1"
#310000
0"
#315000
b1110 !
b1110 $
1"
#320000
0"
#325000
b1111 !
b1111 $
1"
#330000
0"
#335000
b0 !
b0 $
1"
#340000
0"
#345000
b1 !
b1 $
1"
#350000
0"
#355000
b10 !
b10 $
1"
#360000
0"
#365000
b11 !
b11 $
1"
#370000
0"
#375000
b100 !
b100 $
1"
#380000
0"
#385000
b101 !
b101 $
1"
#390000
0"
#395000
b110 !
b110 $
1"
#400000
0"
#405000
b111 !
b111 $
1"
#410000
0"
#415000
b1000 !
b1000 $
1"
#420000
0"
#425000
b1001 !
b1001 $
1"
#430000
0"
#435000
b1010 !
b1010 $
1"
#440000
0"
#445000
b1011 !
b1011 $
1"
#450000
0"
#455000
b1100 !
b1100 $
1"
#460000
0"
#465000
b1101 !
b1101 $
1"
#470000
0"
#475000
b1110 !
b1110 $
1"
#480000
0"
#485000
b1111 !
b1111 $
1"
#490000
0"
#495000
b0 !
b0 $
1"
#500000
0"
#505000
b1 !
b1 $
1"
#510000
0"
#515000
b10 !
b10 $
1"
#520000
0"
#525000
b11 !
b11 $
1"
#530000
0"
#535000
b100 !
b100 $
1"
#540000
0"
#545000
b101 !
b101 $
1"
#550000
0"
#555000
b110 !
b110 $
1"
#560000
0"
#565000
b111 !
b111 $
1"
#570000
0"
#575000
b1000 !
b1000 $
1"
#580000
0"
#585000
b1001 !
b1001 $
1"
#590000
0"
#595000
b1010 !
b1010 $
1"
#600000
0"
#605000
b1011 !
b1011 $
1"
#610000
0"
#615000
b1100 !
b1100 $
1"
#620000
0"
#625000
b1101 !
b1101 $
1"
#630000
0"
#635000
b1110 !
b1110 $
1"
#640000
0"
#645000
b1111 !
b1111 $
1"
#650000
0"
#655000
b0 !
b0 $
1"
#660000
0"
#665000
b1 !
b1 $
1"
#670000
0"
#675000
b10 !
b10 $
1"
#680000
0"
#685000
b11 !
b11 $
1"
#690000
0"
#695000
b100 !
b100 $
1"
#700000
0"
#705000
b101 !
b101 $
1"
#710000
0"
#715000
b110 !
b110 $
1"
#720000
0"
#725000
b111 !
b111 $
1"
#730000
0"
#735000
b1000 !
b1000 $
1"
#740000
0"
#745000
b1001 !
b1001 $
1"
#750000
0"
#755000
b1010 !
b1010 $
1"
#760000
0"
#765000
b1011 !
b1011 $
1"
#770000
0"
#775000
b1100 !
b1100 $
1"
#780000
0"
#785000
b1101 !
b1101 $
1"
#790000
0"
#795000
b1110 !
b1110 $
1"
#800000
0"
#805000
b1111 !
b1111 $
1"
#810000
0"
#815000
b0 !
b0 $
1"
#820000
0"
#825000
b1 !
b1 $
1"
#830000
0"
#835000
b10 !
b10 $
1"
#840000
0"
#845000
b11 !
b11 $
1"
#850000
0"
#855000
b100 !
b100 $
1"
#860000
0"
#865000
b101 !
b101 $
1"
#870000
0"
#875000
b110 !
b110 $
1"
#880000
0"
#885000
b111 !
b111 $
1"
#890000
0"
#895000
b1000 !
b1000 $
1"
#900000
0"
#905000
b1001 !
b1001 $
1"
#910000
0"
#915000
b1010 !
b1010 $
1"
#920000
0"
#925000
b1011 !
b1011 $
1"
#930000
0"
#935000
b1100 !
b1100 $
1"
#940000
0"
#945000
b1101 !
b1101 $
1"
#950000
0"
#955000
b1110 !
b1110 $
1"
#960000
0"
#965000
b1111 !
b1111 $
1"
#970000
0"
#975000
b0 !
b0 $
1"
#980000
0"
#985000
b1 !
b1 $
1"
#990000
0"
#995000
b10 !
b10 $
1"
#1000000
0"
#1005000
b11 !
b11 $
1"
#1010000
0"
#1015000
b100 !
b100 $
1"
